
<filter>
	<rule>
		<id></id>
		<tracker>0100000103</tracker>
		<type>pass</type>
		<interface>wan</interface>
		<ipprotocol>inet</ipprotocol>
		<tag></tag>
		<tagged></tagged>
		<max></max>
		<max-src-nodes></max-src-nodes>
		<max-src-conn></max-src-conn>
		<max-src-states></max-src-states>
		<statetimeout></statetimeout>
		<statetype><![CDATA[keep state]]></statetype>
		<os></os>
		<protocol>tcp</protocol>
		<source>
			<any></any>
		</source>
		<destination>
			<network>(self)</network>
			<port>22</port>
		</destination>
		<descr><![CDATA[Allow SSH]]></descr>
	</rule>
	<rule>
		<type>pass</type>
		<ipprotocol>inet</ipprotocol>
		<descr><![CDATA[Default allow LAN to any rule]]></descr>
		<interface>lan</interface>
		<tracker>0100000101</tracker>
		<source>
			<network>lan</network>
		</source>
		<destination>
			<any></any>
		</destination>
	</rule>
	<rule>
		<type>pass</type>
		<ipprotocol>inet6</ipprotocol>
		<descr><![CDATA[Default allow LAN IPv6 to any rule]]></descr>
		<interface>lan</interface>
		<tracker>0100000102</tracker>
		<source>
			<network>lan</network>
		</source>
		<destination>
			<any></any>
		</destination>
	</rule>
	<rule>
		<id></id>
		<tracker>0100000104</tracker>
		<type>block</type>
		<interface>opt1</interface>
		<ipprotocol>inet</ipprotocol>
		<tag></tag>
		<tagged></tagged>
		<max></max>
		<max-src-nodes></max-src-nodes>
		<max-src-conn></max-src-conn>
		<max-src-states></max-src-states>
		<statetimeout></statetimeout>
		<statetype><![CDATA[keep state]]></statetype>
		<os></os>
		<protocol>tcp</protocol>
		<source>
			<any></any>
		</source>
		<destination>
			<network>(self)</network>
			<port>Management</port>
		</destination>
		<descr><![CDATA[Deny management access]]></descr>
	</rule>
	<rule>
		<id></id>
		<tracker>0100000105</tracker>
		<type>block</type>
		<interface>opt1</interface>
		<ipprotocol>inet</ipprotocol>
		<tag></tag>
		<tagged></tagged>
		<max></max>
		<max-src-nodes></max-src-nodes>
		<max-src-conn></max-src-conn>
		<max-src-states></max-src-states>
		<statetimeout></statetimeout>
		<statetype><![CDATA[keep state]]></statetype>
		<os></os>
		<source>
			<any></any>
		</source>
		<destination>
			<address>CGNAT</address>
		</destination>
		<descr><![CDATA[Deny CGNAT]]></descr>
	</rule>
	<rule>
		<id></id>
		<tracker>0100000106</tracker>
		<type>pass</type>
		<interface>opt1</interface>
		<ipprotocol>inet</ipprotocol>
		<tag></tag>
		<tagged></tagged>
		<max></max>
		<max-src-nodes></max-src-nodes>
		<max-src-conn></max-src-conn>
		<max-src-states></max-src-states>
		<statetimeout></statetimeout>
		<statetype><![CDATA[keep state]]></statetype>
		<os></os>
		<protocol>tcp/udp</protocol>
		<source>
			<any></any>
		</source>
		<destination>
			<network>(self)</network>
			<port>53</port>
		</destination>
		<descr><![CDATA[Allow DNS]]></descr>
	</rule>
	<rule>
		<id></id>
		<tracker>0100000107</tracker>
		<type>pass</type>
		<interface>opt1</interface>
		<ipprotocol>inet</ipprotocol>
		<tag></tag>
		<tagged></tagged>
		<max></max>
		<max-src-nodes></max-src-nodes>
		<max-src-conn></max-src-conn>
		<max-src-states></max-src-states>
		<statetimeout></statetimeout>
		<statetype><![CDATA[keep state]]></statetype>
		<os></os>
		<protocol>icmp</protocol>
		<icmptype>echoreq</icmptype>
		<source>
			<network>opt1</network>
		</source>
		<destination>
			<network>(self)</network>
		</destination>
		<descr><![CDATA[Allow ICMP]]></descr>
	</rule>
	<rule>
		<id></id>
		<tracker>0100000108</tracker>
		<type>block</type>
		<interface>opt1</interface>
		<ipprotocol>inet</ipprotocol>
		<tag></tag>
		<tagged></tagged>
		<max></max>
		<max-src-nodes></max-src-nodes>
		<max-src-conn></max-src-conn>
		<max-src-states></max-src-states>
		<statetimeout></statetimeout>
		<statetype><![CDATA[keep state]]></statetype>
		<os></os>
		<source>
			<any></any>
		</source>
		<destination>
			<address>RFC1918</address>
		</destination>
		<descr><![CDATA[Deny RFC1918 (Isolate subnet)]]></descr>
	</rule>
	<rule>
		<id></id>
		<tracker>0100000109</tracker>
		<type>pass</type>
		<interface>opt1</interface>
		<ipprotocol>inet</ipprotocol>
		<tag></tag>
		<tagged></tagged>
		<max></max>
		<max-src-nodes></max-src-nodes>
		<max-src-conn></max-src-conn>
		<max-src-states></max-src-states>
		<statetimeout></statetimeout>
		<statetype><![CDATA[keep state]]></statetype>
		<os></os>
		<source>
			<network>opt1</network>
		</source>
		<destination>
			<any></any>
		</destination>
		<descr><![CDATA[Default allow rule]]></descr>
	</rule>
	<rule>
		<id></id>
		<tracker>0100000110</tracker>
		<type>block</type>
		<interface>opt2</interface>
		<ipprotocol>inet</ipprotocol>
		<tag></tag>
		<tagged></tagged>
		<max></max>
		<max-src-nodes></max-src-nodes>
		<max-src-conn></max-src-conn>
		<max-src-states></max-src-states>
		<statetimeout></statetimeout>
		<statetype><![CDATA[keep state]]></statetype>
		<os></os>
		<protocol>tcp</protocol>
		<source>
			<any></any>
		</source>
		<destination>
			<network>(self)</network>
			<port>Management</port>
		</destination>
		<descr><![CDATA[Deny management access]]></descr>
	</rule>
	<rule>
		<id></id>
		<tracker>0100000111</tracker>
		<type>block</type>
		<interface>opt2</interface>
		<ipprotocol>inet</ipprotocol>
		<tag></tag>
		<tagged></tagged>
		<max></max>
		<max-src-nodes></max-src-nodes>
		<max-src-conn></max-src-conn>
		<max-src-states></max-src-states>
		<statetimeout></statetimeout>
		<statetype><![CDATA[keep state]]></statetype>
		<os></os>
		<source>
			<any></any>
		</source>
		<destination>
			<address>CGNAT</address>
		</destination>
		<descr><![CDATA[Deny CGNAT]]></descr>
	</rule>
	<rule>
		<id></id>
		<tracker>0100000112</tracker>
		<type>pass</type>
		<interface>opt2</interface>
		<ipprotocol>inet</ipprotocol>
		<tag></tag>
		<tagged></tagged>
		<max></max>
		<max-src-nodes></max-src-nodes>
		<max-src-conn></max-src-conn>
		<max-src-states></max-src-states>
		<statetimeout></statetimeout>
		<statetype><![CDATA[keep state]]></statetype>
		<os></os>
		<protocol>tcp/udp</protocol>
		<source>
			<any></any>
		</source>
		<destination>
			<network>(self)</network>
			<port>53</port>
		</destination>
		<descr><![CDATA[Allow DNS]]></descr>
	</rule>
	<rule>
		<id></id>
		<tracker>0100000113</tracker>
		<type>pass</type>
		<interface>opt2</interface>
		<ipprotocol>inet</ipprotocol>
		<tag></tag>
		<tagged></tagged>
		<max></max>
		<max-src-nodes></max-src-nodes>
		<max-src-conn></max-src-conn>
		<max-src-states></max-src-states>
		<statetimeout></statetimeout>
		<statetype><![CDATA[keep state]]></statetype>
		<os></os>
		<protocol>icmp</protocol>
		<icmptype>echoreq</icmptype>
		<source>
			<network>opt2</network>
		</source>
		<destination>
			<network>(self)</network>
		</destination>
		<descr><![CDATA[Allow ICMP]]></descr>
	</rule>
	<rule>
		<id></id>
		<tracker>0100000114</tracker>
		<type>block</type>
		<interface>opt2</interface>
		<ipprotocol>inet</ipprotocol>
		<tag></tag>
		<tagged></tagged>
		<max></max>
		<max-src-nodes></max-src-nodes>
		<max-src-conn></max-src-conn>
		<max-src-states></max-src-states>
		<statetimeout></statetimeout>
		<statetype><![CDATA[keep state]]></statetype>
		<os></os>
		<source>
			<any></any>
		</source>
		<destination>
			<address>RFC1918</address>
		</destination>
		<descr><![CDATA[Deny RFC1918 (Isolate subnet)]]></descr>
	</rule>
	<rule>
		<id></id>
		<tracker>0100000115</tracker>
		<type>pass</type>
		<interface>opt2</interface>
		<ipprotocol>inet</ipprotocol>
		<tag></tag>
		<tagged></tagged>
		<max></max>
		<max-src-nodes></max-src-nodes>
		<max-src-conn></max-src-conn>
		<max-src-states></max-src-states>
		<statetimeout></statetimeout>
		<statetype><![CDATA[keep state]]></statetype>
		<os></os>
		<source>
			<network>opt2</network>
		</source>
		<destination>
			<any></any>
		</destination>
		<descr><![CDATA[Default allow rule]]></descr>
	</rule>
	<separator>
		<opt1></opt1>
		<opt2></opt2>
	</separator>
</filter>
